Metadata-Version: 2.1
Name: identYwaf
Version: 1.0.127
Summary: Blind WAF identification tool
Home-page: https://github.com/stamparm/identYwaf/
Author: Miroslav Stampar
Author-email: miroslav.stampar@gmail.com
License: MIT License
Download-URL: https://github.com/stamparm/identYwaf/archive/master.zip
Project-URL: Source, https://github.com/stamparm/identYwaf/
Project-URL: Documentation, https://github.com/stamparm/identYwaf/blob/master/README.md
Project-URL: Tracker, https://github.com/stamparm/identYwaf/issues
Platform: UNKNOWN
Classifier: Development Status :: 5 - Production/Stable
Classifier: License :: OSI Approved :: MIT License
Classifier: Natural Language :: English
Classifier: Operating System :: OS Independent
Classifier: Programming Language :: Python
Classifier: Environment :: Console
Classifier: Topic :: Security
